ordeq_args/__init__.py
ordeq_args/_version.py
ordeq_args/command_line_arg.py
ordeq_args/environment_variable.py
ordeq_args/py.typed
ordeq_args-1.0.2.dist-info/licenses/LICENSE
ordeq_args-1.0.2.dist-info/METADATA
ordeq_args-1.0.2.dist-info/WHEEL
ordeq_args-1.0.2.dist-info/top_level.txt
ordeq_args-1.0.2.dist-info/RECORD
