Metadata-Version: 2.4
Name: ordeq_args
Version: 1.0.2
Summary: Argparse and environment variables integration for Ordeq
Author: Niels Neerhoff, Simon Brugman
Maintainer: Niels Neerhoff, Simon Brugman
License-Expression: MIT
Requires-Python: >=3.10
License-File: LICENSE
Requires-Dist: ordeq>=1.2.0
Dynamic: license-file
